{
  "ticker": "AON",
  "sector": "Financial",
  "current_price": 52.92,
  "previous_close": 54.34,
  "open": 52.11,
  "day_low": 51.56,
  "day_high": 53.18,
  "day_range": "51.56 - 53.18",
  "52_week_low": 49.7,
  "52_week_high": 74.26,
  "52_week_range": "49.70 - 74.26",
  "volume": 16071682,
  "avg_volume": 26374889,
  "market_cap": 288269725065,
  "market_cap_display": "$288.27B",
  "beta": 0.3,
  "pe_ratio": 7.94,
  "eps": 6.67,
  "dividend_yield": 0.0,
  "annual_dividend": 0.0,
  "forward_dividend": 0.0,
  "ex_dividend_date": null,
  "earnings_date": "2025-04-17",
  "target_est": 54.17,
  "shares_outstanding": 5447013941,
  "total_return_pct": -57.7,
  "annual_volatility_pct": 30.4,
  "start_price": 125.11
}