{
  "ticker": "HPQ",
  "sector": "Technology",
  "current_price": 304.54,
  "previous_close": 301.99,
  "open": 308.15,
  "day_low": 289.78,
  "day_high": 318.27,
  "day_range": "289.78 - 318.27",
  "52_week_low": 173.58,
  "52_week_high": 318.27,
  "52_week_range": "173.58 - 318.27",
  "volume": 46146193,
  "avg_volume": 23236673,
  "market_cap": 622101935566,
  "market_cap_display": "$622.10B",
  "beta": 0.3,
  "pe_ratio": 29.82,
  "eps": 10.21,
  "dividend_yield": 0.0,
  "annual_dividend": 0.0,
  "forward_dividend": 0.0,
  "ex_dividend_date": null,
  "earnings_date": "2025-04-03",
  "target_est": 321.73,
  "shares_outstanding": 2042772561,
  "total_return_pct": 20.0,
  "annual_volatility_pct": 37.6,
  "start_price": 253.7
}